AUTHORS.txt
LICENSE.txt
MANIFEST.in
README.rst
setup.py
gitrecipe.egg-info/PKG-INFO
gitrecipe.egg-info/SOURCES.txt
gitrecipe.egg-info/dependency_links.txt
gitrecipe.egg-info/entry_points.txt
gitrecipe.egg-info/namespace_packages.txt
gitrecipe.egg-info/not-zip-safe
gitrecipe.egg-info/requires.txt
gitrecipe.egg-info/top_level.txt
recipe/__init__.py
recipe/git/__init__.py