Metadata-Version: 1.0
Name: gitrecipe
Version: 0.0.2
Summary: Simple buildout recipe for downloading git repositories. It uses system git command and its syntax
Home-page: http://github.com/summerisgone/gitrecipe
Author: Ivan Gromov
Author-email: summer.is.gone@gmail.com
License: UNKNOWN
Download-URL: http://github.com/summerisgone/gitrecipe/zipball/0.1
Platform: UNKNOWN
Classifier: Development Status :: 3 - Alpha
Classifier: Framework :: Buildout
Classifier: Intended Audience :: Developers
Classifier: License :: Freely Distributable
Classifier: Natural Language :: Russian
Classifier: Operating System :: Microsoft :: Windows
Classifier: Operating System :: Unix
Classifier: Programming Language :: Python :: 2.5
Classifier: Topic :: Software Development :: Version Control
